cosmodb/__init__.py
cosmodb/get.py
cosmodb/image.py
cosmodb/image_source.py
cosmodb-0.0.2.dist-info/licenses/LICENSE
cosmodb-0.0.2.dist-info/METADATA
cosmodb-0.0.2.dist-info/WHEEL
cosmodb-0.0.2.dist-info/top_level.txt
cosmodb-0.0.2.dist-info/RECORD
