Metadata-Version: 2.4
Name: cosmodb
Version: 0.0.2
Summary: A future-proof database library for Cosmotalker.
Home-page: https://bhuvaneshm.in
Author: Bhuvanesh M
Author-email: contact@bhuvaneshm.in
License: Non-Commercial Custom License
Classifier: Programming Language :: Python :: 3
Classifier: License :: Other/Proprietary License
Classifier: Operating System :: OS Independent
Requires-Python: >=3.6
License-File: LICENSE
Dynamic: author
Dynamic: author-email
Dynamic: classifier
Dynamic: description
Dynamic: description-content-type
Dynamic: home-page
Dynamic: license
Dynamic: license-file
Dynamic: requires-python
Dynamic: summary
